invisibleroads_posts/__init__.py
invisibleroads_posts/constants.py
invisibleroads_posts/models.py
invisibleroads_posts/scripts.py
invisibleroads_posts/tests.py
invisibleroads_posts/variables.py
invisibleroads_posts/views.py
invisibleroads_posts/routines/__init__.py
invisibleroads_posts/routines/cache.py
invisibleroads_posts/routines/configuration.py
invisibleroads_posts-0.7.16.3.dist-info/METADATA
invisibleroads_posts-0.7.16.3.dist-info/WHEEL
invisibleroads_posts-0.7.16.3.dist-info/entry_points.txt
invisibleroads_posts-0.7.16.3.dist-info/top_level.txt
invisibleroads_posts-0.7.16.3.dist-info/zip-safe
invisibleroads_posts-0.7.16.3.dist-info/RECORD
