Metadata-Version: 2.1
Name: invisibleroads-posts
Version: 0.7.16.3
Summary: Web application defaults
Home-page: https://github.com/invisibleroads/invisibleroads-posts
Author: Roy Hyunjin Han
Author-email: rhh@crosscompute.com
License: UNKNOWN
Keywords: web wsgi bfg pylons pyramid invisibleroads
Platform: UNKNOWN
Classifier: Programming Language :: Python
Classifier: Framework :: Pyramid
Classifier: Topic :: Internet :: WWW/HTTP
Classifier: Topic :: Internet :: WWW/HTTP :: WSGI :: Application
Classifier: License :: OSI Approved :: MIT License
Requires-Dist: invisibleroads (>=0.3.3)
Requires-Dist: pyramid
Requires-Dist: dogpile.cache
Requires-Dist: invisibleroads-macros-configuration (>=1.0.6)
Requires-Dist: invisibleroads-macros-descriptor (>=1.0.2)
Requires-Dist: invisibleroads-macros-disk (>=1.1.0)
Requires-Dist: invisibleroads-macros-security (>=1.0.1)
Requires-Dist: invisibleroads-macros-text (>=1.0.3)
Provides-Extra: test
Requires-Dist: pytest-cov ; extra == 'test'
Requires-Dist: webtest ; extra == 'test'
